juryLLM/__init__.py
juryLLM/jury.py
juryLLM/model.py
juryLLM-0.1.2.dist-info/LICENSE
juryLLM-0.1.2.dist-info/METADATA
juryLLM-0.1.2.dist-info/WHEEL
juryLLM-0.1.2.dist-info/top_level.txt
juryLLM-0.1.2.dist-info/RECORD
