Metadata-Version: 2.1
Name: juryLLM
Version: 0.1.2
Summary: An experimental framework for LLM discussions with judge oversight
Home-page: https://github.com/sujithhubpost/juryLLM
Author: Sujith
Project-URL: Bug Reports, https://github.com/yourusername/juryLLM/issues
Project-URL: Source, https://github.com/yourusername/juryLLM
Project-URL: Documentation, https://github.com/yourusername/juryLLM/tree/main/docs
Classifier: Development Status :: 3 - Alpha
Classifier: Intended Audience :: Developers
Classifier: License :: OSI Approved :: MIT License
Classifier: Operating System :: OS Independent
Classifier: Programming Language :: Python :: 3
Classifier: Programming Language :: Python :: 3.8
Classifier: Programming Language :: Python :: 3.9
Classifier: Programming Language :: Python :: 3.10
Classifier: Programming Language :: Python :: 3.11
Classifier: Topic :: Scientific/Engineering :: Artificial Intelligence
Requires-Python: >=3.8
License-File: LICENSE
Requires-Dist: openai>=1.0.0
Requires-Dist: ollama>=0.1.0
Requires-Dist: pydantic>=2.0.0
Requires-Dist: typing-extensions>=4.5.0
Requires-Dist: aiohttp>=3.8.0
Requires-Dist: asyncio>=3.4.3
Requires-Dist: rich>=13.0.0
Provides-Extra: dev
Requires-Dist: pytest>=7.0; extra == "dev"
Requires-Dist: black>=22.0; extra == "dev"
Requires-Dist: isort>=5.0; extra == "dev"
Requires-Dist: mypy>=0.9; extra == "dev"
Requires-Dist: twine>=4.0.0; extra == "dev"
Requires-Dist: build>=0.10.0; extra == "dev"
